wcf/__init__.py
wcf/demo.py
wcf/networks/__init__.py
wcf/networks/models.py
wcf/networks/ptcv_models.py
wcf/networks/resnets.py
wcf/networks/torchvision_models.py
wcf/networks/utils.py
wcf/packages/__init__.py
wcf/packages/template/__init__.py
wcf/packages/template/config.py
wcf/packages/template/dataset.py
wcf/packages/template/dataset_old.py
wcf/packages/template/network.py
wcf/packages/template/predict.py
wcf/packages/template/testing.py
wcf/packages/template/training.py
wcf/packages/template/transforms.py
wcf/utils/__init__.py
wcf/utils/app_utils.py
wcf/utils/encrypt_model.py
wcf/utils/merge_imagefolders.py
wcf/utils/misc.py
wcf/utils/split_trainval.py
wcf/utils/to_onnx.py
wk_classify-0.0.3.5.dist-info/LICENSE
wk_classify-0.0.3.5.dist-info/METADATA
wk_classify-0.0.3.5.dist-info/WHEEL
wk_classify-0.0.3.5.dist-info/entry_points.txt
wk_classify-0.0.3.5.dist-info/top_level.txt
wk_classify-0.0.3.5.dist-info/RECORD
