Metadata-Version: 2.1
Name: wk-classify
Version: 0.0.3.5
Summary: A package of tools for building deep-learning classification programs.
Home-page: https://github.com/Peiiii/wk-classify
Author: Wang Pei
Author-email: 1535376447@qq.com
License: UNKNOWN
Platform: UNKNOWN
Classifier: Programming Language :: Python :: 3
Classifier: License :: OSI Approved :: MIT License
Classifier: Operating System :: OS Independent
Requires-Python: >=3.0
Requires-Dist: wpkit2
Requires-Dist: wpcv
Requires-Dist: pytorchcv
Requires-Dist: vtgui
Requires-Dist: opencv-python
Requires-Dist: pillow
Requires-Dist: torch
Requires-Dist: torchvision
Requires-Dist: tqdm
